[
  {
    "id"          : 1,
    "title"       : "Item 1",
    "thumb"       : "BagGreyGGt1.jpg",
    "description" : "Lorem ipsum dolor sit amet, consectetur adipisicing elit, sed do eiusmod tempor incididunt ut labore et dolore adipiscing elit. Ut enim.",
    "timeleft"    : 2,
    "watchers"    : 12,
    "price"       : 275
  },
  {
    "id"          : 2,
    "title"       : "Bag 2",
    "thumb"       : "BagGreyNY1.jpg",
    "description" : "Lorem ipsum dolor sit amet, consectetur adipisicing elit, sed do eiusmod tempor incididunt ut labore et dolore adipiscing elit. Ut enim.",
    "timeleft"    : 3,
    "watchers"    : 3,
    "price"       : 43
  },
  {
    "id"          : 3,
    "title"       : "Bag 3",
    "thumb"       : "BagGreyOrn1.jpg",
    "description" : "Lorem ipsum dolor sit amet, consectetur adipisicing elit, sed do eiusmod tempor incididunt ut labore et dolore adipiscing elit. Ut enim.",
    "timeleft"    : 2,
    "watchers"    : 12,
    "price"       : 39
  },
  {
    "id"          : 4,
    "title"       : "Bag 4",
    "thumb"       : "BagRedBrd1.jpg",
    "description" : "Lorem ipsum dolor sit amet, consectetur adipisicing elit, sed do eiusmod tempor incididunt ut labore et dolore adipiscing elit. Ut enim.",
    "timeleft"    : 2,
    "watchers"    : 12,
    "price"       : 72
  },
  {
    "id"          : 5,
    "title"       : "Bag 5",
    "thumb"       : "BagRedChrch1.jpg",
    "description" : "Lorem ipsum dolor sit amet, consectetur adipisicing elit, sed do eiusmod tempor incididunt ut labore et dolore adipiscing elit. Ut enim.",
    "timeleft"    : 2,
    "watchers"    : 12,
    "price"       : 84
  },
  {
    "id"          : 6,
    "title"       : "Bag 6",
    "thumb"       : "BagRedGGt1.jpg",
    "description" : "Lorem ipsum dolor sit amet, consectetur adipisicing elit, sed do eiusmod tempor incididunt ut labore et dolore adipiscing elit. Ut enim.",
    "timeleft"    : 2,
    "watchers"    : 12,
    "price"       : 99
  },
  {
    "id"          : 7,
    "title"       : "Bag 7",
    "thumb"       : "BagRedOrn1.jpg",
    "description" : "Lorem ipsum dolor sit amet, consectetur adipisicing elit, sed do eiusmod tempor incididunt ut labore et dolore adipiscing elit. Ut enim.",
    "timeleft"    : 2,
    "watchers"    : 12,
    "price"       : 99
  },
  {
    "id"          : 8,
    "title"       : "Bag 8",
    "thumb"       : "BagRedOwl1.jpg",
    "description" : "Lorem ipsum dolor sit amet, consectetur adipisicing elit, sed do eiusmod tempor incididunt ut labore et dolore adipiscing elit. Ut enim.",
    "timeleft"    : 2,
    "watchers"    : 12,
    "price"       : 99
  }
]
